Metadata-Version: 2.0
Name: lbnotes
Version: 0.1.2
Summary: UNKNOWN
Home-page: https://github.com/weilancys/lbnotes
Author: lightblue
License: UNKNOWN
Platform: UNKNOWN
Requires-Dist: flask
Requires-Dist: flask-simplemde
Requires-Dist: flask-wtf
